streamlit_echarts5/__init__.py
streamlit_echarts5/frontend/build/asset-manifest.json
streamlit_echarts5/frontend/build/index.html
streamlit_echarts5/frontend/build/static/css/main.1ce7c80b.css
streamlit_echarts5/frontend/build/static/css/main.1ce7c80b.css.map
streamlit_echarts5/frontend/build/static/js/main.da120fc3.js
streamlit_echarts5/frontend/build/static/js/main.da120fc3.js.LICENSE.txt
streamlit_echarts5/frontend/build/static/js/main.da120fc3.js.map
streamlit_echarts5-1.0.0.dist-info/LICENSE
streamlit_echarts5-1.0.0.dist-info/METADATA
streamlit_echarts5-1.0.0.dist-info/WHEEL
streamlit_echarts5-1.0.0.dist-info/top_level.txt
streamlit_echarts5-1.0.0.dist-info/RECORD
