Metadata-Version: 2.1
Name: streamlit-echarts5
Version: 1.0.0
Summary: Echarts5 custom component for Streamlit
Author-email: Qin Hu <hu578344563@hotmail.com>
Project-URL: Homepage, https://github.com/CyberQin/streamlit-echarts5
Requires-Python: >=3.9
License-File: LICENSE
Requires-Dist: pyecharts >=1.9
Requires-Dist: simplejson >=3.0
Requires-Dist: streamlit >=0.63
